pcmer/__init__.py
pcmer/features.py
physicochemical_mers-1.0.0.dist-info/LICENSE
physicochemical_mers-1.0.0.dist-info/METADATA
physicochemical_mers-1.0.0.dist-info/WHEEL
physicochemical_mers-1.0.0.dist-info/top_level.txt
physicochemical_mers-1.0.0.dist-info/RECORD
