Metadata-Version: 2.1
Name: physicochemical-mers
Version: 1.0.0
Summary: A new profiling approach for DNA sequences based on the nucleotides' physicochemical features
Home-page: https://github.com/AMshoka/PC-mer_Corona
Author: Amirhossein Mohammadi
Author-email: a.h.mohammadi1376@gmail.com
Project-URL: Bug Tracker, https://github.com/AMshoka/PC-mer_Corona/issues
Classifier: Programming Language :: Python :: 3
Classifier: License :: OSI Approved :: MIT License
Classifier: Operating System :: OS Independent
Requires-Python: >=3.6
License-File: LICENSE
